remotable/__init__.py
remotable/__main__.py
remotable-1.2.0.dist-info/LICENSE
remotable-1.2.0.dist-info/METADATA
remotable-1.2.0.dist-info/WHEEL
remotable-1.2.0.dist-info/top_level.txt
remotable-1.2.0.dist-info/RECORD
