Metadata-Version: 2.1
Name: remotable
Version: 1.2.0
Summary: Remote virtual tables for SQLite, using any Python dbapi driver
Author-email: Steve Russo <svrusso1@gmail.com>
Project-URL: Homepage, https://github.com/transistor1/remotable
Project-URL: Bug Tracker, https://github.com/transistor1/remotable/issues
Classifier: Programming Language :: Python :: 3
Classifier: License :: OSI Approved :: MIT License
Classifier: Operating System :: OS Independent
Requires-Python: >=3.9
License-File: LICENSE
Requires-Dist: apsw (>=3.39.4.0)
